sreeclassifier/__init__.py
sreeclassifier/core.py
sreeclassifier/imagenet_classes.txt
sreeclassifier/utils.py
sreeclassifier-1.0.0.dist-info/LICENSE
sreeclassifier-1.0.0.dist-info/METADATA
sreeclassifier-1.0.0.dist-info/WHEEL
sreeclassifier-1.0.0.dist-info/top_level.txt
sreeclassifier-1.0.0.dist-info/RECORD
