Metadata-Version: 2.1
Name: sreeclassifier
Version: 1.0.0
Summary: Image classification using Vision Transformer (ViT)
Author: Manchala Sreekanth
Author-email: manchalasreekanth999@gmail.com
Requires-Python: >=3.7
License-File: LICENSE
Requires-Dist: torch (>=2.0.0)
Requires-Dist: torchvision (>=0.15.0)
Requires-Dist: Pillow (>=9.0.0)
